Metadata-Version: 2.1
Name: matplotvideo
Version: 0.0.2
Summary: Syncing matplotlib and video
Home-page: https://github.com/PySport/matplotvideo
Author: Koen Vossen
Author-email: info@koenvossen.nl
License: MIT
Platform: UNKNOWN
Classifier: Intended Audience :: Developers
Classifier: Intended Audience :: Science/Research
Classifier: Programming Language :: Python :: 3
Classifier: Programming Language :: Python :: 3.6
Classifier: Programming Language :: Python :: 3.7
Classifier: Programming Language :: Python :: 3.8
Classifier: License :: OSI Approved :: MIT License
Classifier: Topic :: Scientific/Engineering
Classifier: Framework :: Matplotlib
